nautobot_move/__init__.py
nautobot_move/forms.py
nautobot_move/replace_switch_utils.py
nautobot_move/signals.py
nautobot_move/template_content.py
nautobot_move/templates/nautobot_move/inc/buttons.html
nautobot_move/templates/nautobot_move/install.html
nautobot_move/templates/nautobot_move/replace.html
nautobot_move/templates/nautobot_move/replace_success.html
nautobot_move/templates/nautobot_move/reverse_install.html
nautobot_move/templates/nautobot_move/reverse_replace.html
nautobot_move/urls.py
nautobot_move/views.py
nautobot_move-3.0.2.dist-info/METADATA
nautobot_move-3.0.2.dist-info/WHEEL
nautobot_move-3.0.2.dist-info/licenses/LICENSE.txt
nautobot_move-3.0.2.dist-info/RECORD
