Metadata-Version: 2.4
Name: nautobot-move
Version: 3.0.2
Summary: A Nautobot plugin for moving devices
License: Apache-2.0
License-File: LICENSE.txt
Author: Gesellschaft für wissenschaftliche Datenverarbeitung mbH Göttingen
Requires-Python: >=3.11,<3.13
Classifier: License :: OSI Approved :: Apache Software License
Classifier: Programming Language :: Python :: 3
Classifier: Programming Language :: Python :: 3.11
Classifier: Programming Language :: Python :: 3.12
Requires-Dist: nautobot (>=2.0.0,<3.0.0)
Requires-Dist: nautobot-bgp-models (>=2.0.0,<3.0.0)
Requires-Dist: nautobot-cable-utils (>=1.0.0,<2.0.0)
Requires-Dist: nautobot-evpn (>=1.0.0,<2.0.0)
Requires-Dist: nautobot-sfp-inventory (>=1.1.1,<2.0.0)
